grammatron/__init__.py
grammatron/dubs/__init__.py
grammatron/dubs/algorithms/__init__.py
grammatron/dubs/algorithms/astar/__init__.py
grammatron/dubs/algorithms/astar/astar.py
grammatron/dubs/algorithms/astar/astar_parser.py
grammatron/dubs/algorithms/astar/graph_builder.py
grammatron/dubs/algorithms/regex/__init__.py
grammatron/dubs/algorithms/regex/regex_builder.py
grammatron/dubs/algorithms/regex/regex_parser.py
grammatron/dubs/core/__init__.py
grammatron/dubs/core/constant_dub.py
grammatron/dubs/core/dub.py
grammatron/dubs/core/grammar_adoptable_dub.py
grammatron/dubs/core/iteration_dub.py
grammatron/dubs/core/list_dub.py
grammatron/dubs/core/parser_intructions.py
grammatron/dubs/core/sequence_dub.py
grammatron/dubs/core/subsequence_dub.py
grammatron/dubs/core/template_dub_base.py
grammatron/dubs/core/template_dubs.py
grammatron/dubs/core/to_str_dub.py
grammatron/dubs/core/variable_dub.py
grammatron/dubs/implementation/__init__.py
grammatron/dubs/implementation/categorical_variable_dub.py
grammatron/dubs/implementation/int_dub.py
grammatron/dubs/implementation/options_dub.py
grammatron/globalization/__init__.py
grammatron/globalization/date_dub.py
grammatron/globalization/language_dispatch_dub.py
grammatron/globalization/month_dub.py
grammatron/globalization/plural_agreement.py
grammatron/globalization/timedelta_dub.py
grammatron/globalization/weekday_dub.py
grammatron/globalization/year_dub.py
grammatron/grammars/__init__.py
grammatron/grammars/grammar_setter.py
grammatron/grammars/common/__init__.py
grammatron/grammars/common/plural_agreement.py
grammatron/grammars/common/word_processor.py
grammatron/grammars/en/__init__.py
grammatron/grammars/en/grammar_rule.py
grammatron/grammars/en/plural_agreement.py
grammatron/grammars/en/word_tools.py
grammatron/grammars/ru/__init__.py
grammatron/grammars/ru/categories.py
grammatron/grammars/ru/declinator.py
grammatron/grammars/ru/grammar_rule.py
grammatron/grammars/ru/plural_agreement.py
kaia_grammatron-4.0.9.dist-info/METADATA
kaia_grammatron-4.0.9.dist-info/WHEEL
kaia_grammatron-4.0.9.dist-info/top_level.txt
kaia_grammatron-4.0.9.dist-info/RECORD
