Metadata-Version: 2.4
Name: kaia-grammatron
Version: 4.0.9
Summary: Library that allows you to define structured utterances
Author-email: Yuri Okulovsky <yuri.okulovsky@gmail.com>
License-Expression: LGPL-3.0-or-later
Project-URL: repository, https://github.com/okulovsky/kaia/tree/main/grammatron
Classifier: Programming Language :: Python :: 3.10
Classifier: Programming Language :: Python :: 3.11
Classifier: Programming Language :: Python :: 3.12
Classifier: Programming Language :: Python :: 3.13
Classifier: Intended Audience :: Developers
Classifier: Intended Audience :: Science/Research
Classifier: Intended Audience :: Information Technology
Classifier: Topic :: Scientific/Engineering :: Artificial Intelligence
Classifier: Development Status :: 4 - Beta
Requires-Python: <4.0,>=3.10
Requires-Dist: yo_fluq
Requires-Dist: kaia-foundation
Requires-Dist: numpy
Requires-Dist: pandas
Requires-Dist: num2words
Requires-Dist: networkx
Requires-Dist: regex
Requires-Dist: inflect
Requires-Dist: lemminflect
Requires-Dist: pymorphy3
Provides-Extra: dev
Requires-Dist: tox; extra == "dev"
Requires-Dist: tox-conda; extra == "dev"
Requires-Dist: twine; extra == "dev"
